unis3/__init__.py
unis3/files.py
unis3/unis3.py
unis3/tests/__init__.py
unis3/tests/test_unis3.py
django_unis3-2.2.0.dist-info/LICENSE
django_unis3-2.2.0.dist-info/METADATA
django_unis3-2.2.0.dist-info/WHEEL
django_unis3-2.2.0.dist-info/top_level.txt
django_unis3-2.2.0.dist-info/RECORD
