Metadata-Version: 2.1
Name: django-unis3
Version: 2.2.0
Summary: S3 Django Storage.
Home-page: https://git.unistra.fr/di/cesar/django-unis3.git
Author: di-dip-unistra
Author-email: dnum-dip@unistra.fr
Maintainer: di-dip-unistra
Maintainer-email: dnum-dip@unistra.fr
License: GPLv3
Keywords: django,s3,Université de Strasbourg
Platform: UNKNOWN
Requires-Dist: s3-local-endpoint (==1.0.4)
Requires-Dist: Django (>1.11)
Requires-Dist: requests
